[
    {
        "user": "U20303074",
        "document_type": "DNI",
        "document_number": "7599999",
        "names": "Alexandra",
        "last_names": "Vasquez",
        "email": "alexa@gmail.com",
        "address": "San Martin de Porres",
        "campus": "Lima Norte",
        "phone_number": "9808080",
        "college_career": "Ingenieria de Software",
        "course": "6",
        "gender": "F",
        "age": "20"
    },
    {
        "user": "U20303075",
        "document_type": "DNI",
        "document_number": "75666666",
        "names": "Ron",
        "last_names": "Wisly",
        "email": "ron@gmail.com",
        "address": "Los Olivos Izaguirre",
        "campus": "Lima Sur",
        "phone_number": "910101010",
        "college_career": "Ingenieria de Sistemas",
        "course": "7",
        "gender": "M",
        "age": "24"
    }
]